Serialization/__init__.py
Serialization/base_serializer.py
Serialization/dict_serializer.py
Serialization/json_serializer.py
Serialization/serializers_factory.py
Serialization/type_constants.py
Serialization/xml_serializer.py
ShunkoSerialization-0.1.1.dist-info/METADATA
ShunkoSerialization-0.1.1.dist-info/WHEEL
ShunkoSerialization-0.1.1.dist-info/top_level.txt
ShunkoSerialization-0.1.1.dist-info/RECORD
